opal_fetcher_cosmos/__init__.py
opal_fetcher_cosmos/provider.py
opal_fetcher_cosmos-0.0.3.dist-info/LICENSE
opal_fetcher_cosmos-0.0.3.dist-info/METADATA
opal_fetcher_cosmos-0.0.3.dist-info/WHEEL
opal_fetcher_cosmos-0.0.3.dist-info/top_level.txt
opal_fetcher_cosmos-0.0.3.dist-info/RECORD
