Metadata-Version: 2.1
Name: opal-fetcher-cosmos
Version: 0.0.3
Summary: An OPAL fetch provider to bring authorization state from CosmosDB.
Author: Avo Sepp
License: Apache-2.0
Project-URL: Homepage, https://github.com/avo-sepp/opal-fetcher-cosmos
Project-URL: Source, https://github.com/avo-sepp/opal-fetcher-cosmos
Project-URL: Bug Tracker, https://github.com/avo-sepp/opal-fetcher-cosmos/issues
Keywords: Open Policy Agent,OPA,OPAL,Open Policy Administration Layer,Permit.io
Classifier: Operating System :: OS Independent
Classifier: License :: OSI Approved :: Apache Software License
Classifier: Topic :: Software Development :: Libraries :: Python Modules
Classifier: Programming Language :: Python
Classifier: Programming Language :: Python :: 3
Requires-Python: >=3.7
License-File: LICENSE
Requires-Dist: setuptools-scm
Requires-Dist: opal-common (>=0.1.11)
Requires-Dist: azure-cosmos
Requires-Dist: azure-identity
Requires-Dist: jq
Requires-Dist: wait-for-it
Requires-Dist: pydantic
Requires-Dist: tenacity
Requires-Dist: click
